COPYING
MANIFEST.in
README.rst
setup.py
cpl/CPL_library.c
cpl/CPL_library.h
cpl/CPL_recipe.c
cpl/__init__.py
cpl/cpl_api.h
cpl/dfs.py
cpl/esorex.py
cpl/frames.py
cpl/logger.py
cpl/md5sum.py
cpl/param.py
cpl/recipe.py
cpl/result.py
cpl/version.py
doc/Makefile
doc/conf.py
doc/dfs.rst
doc/esorex.rst
doc/frames.rst
doc/index.rst
doc/install.rst
doc/msg.rst
doc/parallel.rst
doc/param.rst
doc/recipe.rst
doc/restrictions.rst
doc/result.rst
doc/tutorial.rst
python_cpl.egg-info/PKG-INFO
python_cpl.egg-info/SOURCES.txt
python_cpl.egg-info/dependency_links.txt
python_cpl.egg-info/requires.txt
python_cpl.egg-info/top_level.txt
test/TestRecipe.py
test/rtest.c